{"bill_number":111615,"ordinance_number":118492,"status":"passed","date_passed":"1997-02-18T00:00:00+00:00","date_filed":"1997-02-25T00:00:00+00:00","date_of_signature":"1997-02-18T00:00:00+00:00","date_introduced":"1997-02-03T00:00:00+00:00","index_terms":["CITY LIGHT","EASEMENTS","DRAINAGE","KING COUNTY"],"fiscal_note":null,"summary":"AN ORDINANCE relating to the Seattle City Light Department, authorizing the grant of an easement for surface water drainage, upon, and across a portion of City of Seattle's Duwamish Substation in the northwest quarter of Section 4 and the northeast quarter of Section 5, Township 23 North, Range 4 East, W.M., in King County, Washington (P.M. \\#230404-2-302).  ","committee":"Utilities and Environmental Management","sponsor":"PAGELER","vote":"8-0"}