{"bill_number":17484,"ordinance_number":29174,"status":"passed","date_passed":"1912-04-01T00:00:00+00:00","date_filed":"1912-04-03T00:00:00+00:00","date_of_signature":"1912-04-03T00:00:00+00:00","date_introduced":"1912-03-25T00:00:00+00:00","index_terms":["LAW DEPARTMENT","BONDS","SALES","FINANCE"],"fiscal_note":null,"summary":"An Ordinance authorizing the Corporation Counsel to incur an expenditure in the employment of the necessary clerical assistance in the preparation of transcripts of record covering the issuance and sale of $500,000 Park Bonds and $125,000 Tuberculosis Hospital Bonds, voted at an election held in The City of Seattle on the 5th day of March, 1912.  ","committee":"Finance"}