{"bill_number":27414,"ordinance_number":38244,"status":"passed","date_passed":"1918-02-25T00:00:00+00:00","date_filed":"1918-02-26T00:00:00+00:00","date_of_signature":"1918-02-26T00:00:00+00:00","date_introduced":"1918-02-18T00:00:00+00:00","index_terms":["PUBLIC UTILITIES DEPARTMENT","MUNICIPAL STREET RAILWAY SYSTEM","CITY EMPLOYEES","WAGES AND SALARIES"],"fiscal_note":null,"summary":"An ordinance creating the position of inspector in the city railway division of the Department of Public Utilities.  ","committee":"Department Efficiency, Judiciary"}