{"bill_number":95222,"ordinance_number":103493,"status":"passed","date_passed":"1974-06-24T00:00:00+00:00","date_filed":"1974-06-27T00:00:00+00:00","date_of_signature":"1974-06-27T00:00:00+00:00","date_introduced":"1974-06-17T00:00:00+00:00","index_terms":["BOARD OF PUBLIC WORKS","CITY EMPLOYEES","WAGES AND SALARIES"],"references":"Related: CF 278980  ","fiscal_note":null,"summary":"AN ORDINANCE relating to the Board of Public Works; providing for an adjustment in compensation for the position of Executive Secretary, Board of Public Works.  ","committee":"Human Resources and Judicial","sponsor":"WILLIAMS"}