{"bill_number":106274,"ordinance_number":113558,"status":"passed","date_passed":"1987-08-10T00:00:00+00:00","date_of_signature":"1987-08-20T00:00:00+00:00","date_introduced":"1987-08-03T00:00:00+00:00","index_terms":["ENGINEERING DEPARTMENT","LAND ACQUISITION","DRAINAGE","WEST SEATTLE","BUDGET","APPROPRIATION"],"fiscal_note":null,"summary":"AN ORDINANCE relating to the Engineering Dept., authorizing the Director of Engineering to appraise, negotiate for and acquire real property and property rights, and to proceed with construction of the 47th Avenue Southwest Spot Drainage Project; increasing expenditure allowances in the 1987 Budget of the Seattle Engineering Department; and making appropriations from the Engineering Dept. Operating Fund and the Sewer Fund therefor.  ","committee":"Finance and Personnel","sponsor":"GALLE","vote":"6-0"}