{"bill_number":79452,"ordinance_number":87997,"status":"passed","date_passed":"1959-03-02T00:00:00+00:00","date_filed":"1959-03-03T00:00:00+00:00","date_of_signature":"1959-03-03T00:00:00+00:00","date_introduced":"1959-02-24T00:00:00+00:00","index_terms":["EASEMENTS","STORM SEWERS","KING COUNTY","DRAINAGE"],"references":"Related: CF 236556  ","fiscal_note":null,"summary":"An ordinance accepting an easement from Gilbert R. Almquist and Clara L. Almquist, his wife, over a portion of Lots 17 and 18, Lake Boren Subdivision (unrecorded) for a drain and blow-off, and making an appropriation from the Water Fund in connection therewith.  ","committee":"Finance and City Utilities"}