{"bill_number":91181,"ordinance_number":99590,"status":"passed","date_passed":"1971-01-11T00:00:00+00:00","date_filed":"1971-01-14T00:00:00+00:00","date_of_signature":"1971-01-14T00:00:00+00:00","date_introduced":"1971-01-04T00:00:00+00:00","index_terms":["DRUG ENFORCEMENT","DRUG SALES","DRUG ABUSE"],"references":"Related: CF 268168. Amending: Ord 40149.  ","fiscal_note":null,"summary":"AN ORDINANCE amending Ordinance 40149 by adding thereto a new section designated Section 7-A making unlawful certain offers or agreements to furnish, facilitate or arrange the furnishing of certain narcotic or dangerous drugs.  ","committee":"Public Safety"}