{"bill_number":91232,"ordinance_number":99650,"status":"passed","date_passed":"1971-02-08T00:00:00+00:00","date_filed":"1971-02-11T00:00:00+00:00","date_of_signature":"1971-02-11T00:00:00+00:00","date_introduced":"1971-01-25T00:00:00+00:00","index_terms":["PERMITS","STREETS","BUILDING CODES","SAFETY","ENVIRONMENTAL PROTECTION","AIR POLLUTION"],"references":"Related: CF 266654. Amending: Ord 90047.  ","fiscal_note":null,"summary":"AN ORDINANCE relating to street use and street use permits and amending Section 15 of Ordinance 90047 to require work to be done in compliance with the Washington Clean Air Act.  ","committee":"Public Safety"}