{"bill_number":70070,"ordinance_number":78740,"status":"passed","date_passed":"1950-02-27T00:00:00+00:00","date_filed":"1950-02-28T00:00:00+00:00","date_of_signature":"1950-02-28T00:00:00+00:00","date_introduced":"1950-02-20T00:00:00+00:00","index_terms":["LOCAL IMPROVEMENT DISTRICTS","STREET CONSTRUCTION","SANITARY SEWERS","STORM SEWERS","SIDE SEWERS","WATER MAINS","FIRE HYDRANTS","SIDEWALKS","GRADING","LAWTON PARK","MAGNOLIA"],"references":"Related: Ord 78015  ","fiscal_note":null,"summary":"An ordinance approving and confirming the assessment and assessment roll of Local Improvement District No. 5912 for the improvement of Commodore Way, from 23rd Avenue West to 40th Avenue West; and certain parts of certain other streets and avenues; by paving and otherwise improving the same; under Ordinance No. 78015, and levying and assessing the amounts thereof against the several lots, tracts, parcels of land and other property as shown on said roll, establishing a Local Improvement Fund.  ","committee":"Streets and Sewers"}