{"bill_number":96142,"ordinance_number":104405,"status":"passed","date_passed":"1975-04-07T00:00:00+00:00","date_filed":"1975-04-09T00:00:00+00:00","date_of_signature":"1975-04-09T00:00:00+00:00","date_introduced":"1975-03-10T00:00:00+00:00","index_terms":["CITY EMPLOYEES","SEATTLE KING COUNTY OMBUDSMAN","WAGES AND SALARIES"],"references":"Related: CF 280926  ","fiscal_note":null,"summary":"AN ORDINANCE making an appropriation from the Emergency Fund to increase the budget allowance for Object of Expenditure \"4113 - Ombudsman\" in the 1975 Budget, Finance-General, and declaring the emergency therefor.  ","committee":"Human Resources and Judicial","sponsor":"WILLIAMS"}