{"bill_number":96498,"ordinance_number":104711,"status":"passed","date_passed":"1975-07-14T00:00:00+00:00","date_filed":"1975-07-18T00:00:00+00:00","date_of_signature":"1975-07-18T00:00:00+00:00","date_introduced":"1975-07-07T00:00:00+00:00","index_terms":["AGRICULTURE DEPARTMENT","GRANTS","FOOD PROGRAMS","CHILDREN","STUDENTS","YOUTH","NUTRITION","LOW INCOME","FINANCE","CITY EMPLOYEES","WAGES AND SALARIES","CONTRACTS"],"references":"Related: CF 281656  ","fiscal_note":null,"summary":"AN ORDINANCE relating to the Department of Human Resources; authorizing an agreement with the United States of America, Department of Agriculture, for financial assistance for the City's \"Summer Sack Lunch Program\" for disadvantaged youth, authorizing a contract with a food service vendor for operation of said program, increasing certain objects of expenditure in the 1975 Budget of the Department of Human Resources, making a reimbursable appropriation from the Emergency Fund and declaring the emergency therefor.  ","committee":"Human Resources and Judicial","sponsor":"WILLIAMS"}