{"bill_number":22200,"ordinance_number":33474,"status":"passed","date_passed":"1914-08-03T00:00:00+00:00","date_filed":"1914-08-06T00:00:00+00:00","date_of_signature":"1914-08-06T00:00:00+00:00","date_introduced":"1914-07-27T00:00:00+00:00","index_terms":["STREET CONSTRUCTION","SIDEWALKS","NORTH QUEEN ANNE","QUEEN ANNE"],"references":"Related: CF 56317  ","fiscal_note":null,"summary":"An Ordinance providing for the improvement of Etruria Street, from Nickerson Street to a point one hundred eighty (180) feet west of Warren Avenue; Warren Avenue, from Florentia Street to Nickerson Street; The Southwesterly side of Nickerson Street from Florentia Street to Warren Avenue; by the construction of concrete walks, with all necessary cross walks, all in accordance with Majority Petition, File No. 56317, of the City of Seattle, creating a local improvement district therefor, and providing that payment of said improvement be made by special assessments upon property in said district payable by mode of \"Payment by Bonds\".  "}