{"bill_number":14588,"ordinance_number":26498,"status":"passed","date_passed":"1911-02-27T00:00:00+00:00","date_filed":"1911-02-28T00:00:00+00:00","date_of_signature":"1911-02-28T00:00:00+00:00","date_introduced":"1911-02-20T00:00:00+00:00","index_terms":["STREET CONSTRUCTION","SIDEWALKS","WEST QUEEN ANNE","QUEEN ANNE","INTERBAY"],"references":"Repealing: Ord 19032  ","fiscal_note":null,"summary":"An ordinance repealing Ordinance No. 19032 providing for the improvement of 14th Avenue West et al, in the City of Seattle, by concrete walks, etc., approved August 19, 1908.  ","committee":"Streets"}