{"bill_number":68220,"ordinance_number":76918,"status":"passed","date_passed":"1948-04-05T00:00:00+00:00","date_filed":"1948-04-08T00:00:00+00:00","date_of_signature":"1948-04-08T00:00:00+00:00","date_introduced":"1948-03-29T00:00:00+00:00","index_terms":["PARKS","IMPROVEMENT","PARKS DEPARTMENT","FINANCE"],"references":"Related: CF 197935  ","fiscal_note":null,"summary":"An ordinance relating to the Department of Parks and making an appropriation of $104,948.73 from the Seattle Park Improvement-State Development Fund.  ","committee":"Finance and Harbor & Public Grounds"}