{"bill_number":114314,"ordinance_number":120924,"status":"passed","date_passed":"2002-09-16T00:00:00+00:00","date_filed":"2002-09-24T00:00:00+00:00","date_of_signature":"2002-09-23T00:00:00+00:00","date_introduced":"2002-09-09T00:00:00+00:00","index_terms":["SIGNS AND BILLBOARDS","LAND USE CODE","LAND USE REGULATIONS","LAND USE PERMITS","ADMINISTRATIVE PROCEDURES","RAINIER BEACH","RAINIER VALLEY"],"references":"Amending: Ord 120388  ","fiscal_note":null,"summary":"AN ORDINANCE relating to land use and zoning, amending the list of sign kiosks authorized in subsection 23.55.015E of the Seattle Municipal Code.  ","committee":"Full Council","sponsor":"NICASTRO","vote":"9-0"}