{"bill_number":29194,"ordinance_number":39889,"status":"passed","date_passed":"1919-09-15T00:00:00+00:00","date_filed":"1919-09-17T00:00:00+00:00","date_of_signature":"1919-09-17T00:00:00+00:00","date_introduced":"1919-09-08T00:00:00+00:00","index_terms":["TRANSFERRING FUNDS","KING COUNTY","INTERLOCAL AGREEMENTS","WATER FUND","WATER DEPARTMENT","AUDITS"],"fiscal_note":null,"summary":"An Ordinance appropriating money from the Water Fund to the County Treasurer of King County, Washington, to reimburse King County for money expended in payment of state accountants for services rendered the City of Seattle in the examination of the books and accounts of the Water Department.  ","committee":"Finance"}