{"bill_number":112382,"ordinance_number":119176,"status":"passed","date_passed":"1998-10-05T00:00:00+00:00","date_filed":"1998-10-12T00:00:00+00:00","date_of_signature":"1998-10-12T00:00:00+00:00","date_introduced":"1998-09-28T00:00:00+00:00","index_terms":["CITY LIGHT","ENVIRONMENTAL PROTECTION","ENERGY CONSERVATION","GRANTS","US GOVERNMENT"],"references":"Related: Ord 118597  ","fiscal_note":null,"summary":"AN ORDINANCE relating to the City Light Department; authorizing continued participation in the Cities for Climate Protection Campaign and the Climate Wise Local Government/Industrial Partnership Program; authorizing and implementing agreements; and increasing expenditure allowances in the 1998 Adopted Budget of the City Light Department for the purpose of fulfilling the grant requirements, all by a three-fourths vote of the City Council.  ","committee":"Utilities and Environmental Management","sponsor":"PAGELER","vote":"8-0 (Excused: McIver)"}