{"bill_number":116089,"ordinance_number":122600,"status":"passed","date_passed":"2007-12-17T00:00:00+00:00","date_filed":"2007-12-20T00:00:00+00:00","date_of_signature":"2007-12-20T00:00:00+00:00","date_introduced":"2007-11-26T00:00:00+00:00","index_terms":["COMPREHENSIVE PLAN","INDUSTRIAL DISTRICTS","","INDUSTRIAL DISTRICT","INDUSTRIAL DEVELOPMENT","DEVELOPMENT ACTIVITIES","ECONOMIC DEVELOPMENT. MANUFACTURING"],"fiscal_note":"[Fiscal Note to Council Bill](http://clerk.seattle.gov/~public/fnote/116089.htm)[](#h1)[](#h3)116089","summary":"AN ORDINANCE amending the Seattle Comprehensive Plan to incorporate a change proposed as part of the 2007 Comprehensive Plan annual amendment process for a new policy governing expansion of major employers located in manufacturing/industrial centers.  ","committee":"Urban Development and Planning","sponsor":"STEINBRUECK","vote":"8-0 (Disqualified from voting: Steinbrueck)","electronic_copy":"[PDF scan of Ordinance No. 122600](/~archives/Ordinances/Ord_122600.pdf)"}