{"bill_number":116128,"ordinance_number":122624,"status":"passed","date_passed":"2008-02-04T00:00:00+00:00","date_filed":"2008-02-07T00:00:00+00:00","date_of_signature":"2008-02-07T00:00:00+00:00","date_introduced":"2008-01-28T00:00:00+00:00","index_terms":["INTERNATIONAL DISTRICT","CENTRAL AREA","SUBDIVISION","LAND USE PERMITS"],"references":"Related: CF 307278  ","fiscal_note":"[Fiscal Note to Council Bill](http://clerk.seattle.gov/~public/fnote/116128.htm)[](#h1)[](#h3)116128","summary":"AN ORDINANCE approving and confirming the plat of \"Wyngale's 3rd Addition to the City of Seattle\" in a portion of Section 4, Township 24 North, Range 4 East, W.M., in King County, Washington.  ","committee":"Full Council","sponsor":"CLARK","vote":"9-0","electronic_copy":"[PDF scan of Ordinance No. 122624](/~archives/Ordinances/Ord_122624.pdf)"}