{"bill_number":116416,"ordinance_number":122890,"status":"passed","date_passed":"2008-12-15T00:00:00+00:00","date_filed":"2008-12-22T00:00:00+00:00","date_of_signature":"2008-12-19T00:00:00+00:00","date_introduced":"2008-12-01T00:00:00+00:00","index_terms":["LAND ACQUISITION","DEPARTMENT OF PARKS AND RECREATION","SCHOOL DISTRICT 1 CROWN HILL","PARKS"],"fiscal_note":"[Fiscal Note to Council Bill](http://clerk.seattle.gov/~public/fnote/116416.htm)[](#h1)[](#h3)116416","summary":"AN ORDINANCE authorizing the purchase, for park, open space, and recreation purposes, of real property commonly known as a portion of the former Crown Hill Elementary School, located at 9089 Holman Road Northwest, from Seattle School District No. 1, authorizing acceptance of the deed, authorizing the creation of an Opportunity Fund Project consistent with the requirements of Ordinance 120024, making appropriations, amending the 2008-2013 Capital Improvement Program, and authorizing the loan of funds from the City's Consolidated (Residual) Cash Pool, or its participating funds, to the 2000 Parks Levy Fund, all by a three-fourths vote of the City Council.  ","committee":"Parks and Seattle Center","sponsor":"RASMUSSEN","vote":"9-0","electronic_copy":"[PDF scan of Ordinance No. 122890](/~archives/Ordinances/Ord_122890.pdf)"}