{"bill_number":116710,"ordinance_number":123203,"status":"passed","date_passed":"2009-12-14T00:00:00+00:00","date_filed":"2009-12-22T00:00:00+00:00","date_of_signature":"2009-12-21T00:00:00+00:00","date_introduced":"2009-11-02T00:00:00+00:00","index_terms":["LANDMARKS","HISTORIC BUILDINGS AND SITES","BELLTOWN"],"fiscal_note":"[Fiscal Note to Council Bill](http://clerk.seattle.gov/~public/fnote/116710.htm)[](#h1)[](#h3)116710","summary":"AN ORDINANCE relating to historic preservation, imposing controls upon the William Tell Hotel, a landmark designated by the Landmarks Preservation Board under Chapter 25.12 of the Seattle Municipal Code, and adding it to the Table of Historical Landmarks contained in Chapter 25.32 of the Seattle Municipal Code.  ","committee":"Parks and Seattle Center","sponsor":"RASMUSSEN","vote":"9-0","electronic_copy":"[PDF scan of Ordinance No. 123203](/~archives/Ordinances/Ord_123203.pdf)"}