{"bill_number":7572,"ordinance_number":20211,"status":"passed","date_passed":"1909-02-15T00:00:00+00:00","date_filed":"1909-02-20T00:00:00+00:00","date_of_signature":"1909-02-20T00:00:00+00:00","date_introduced":"1909-02-08T00:00:00+00:00","index_terms":["ASSESSMENT","MANN","CENTRAL AREA"],"references":"Related: Ord 15277  ","fiscal_note":null,"summary":"An Ordinance providing for the rebating and refunding of the excess portions of all assessments levied for the improvement of Temple Place, by grading and constructing concrete sidewalks thereon, as provided for by Ordinance No. 15277, creating Local Improvement District No. 1401.  ","committee":"Finance"}