{"bill_number":72022,"ordinance_number":80653,"status":"passed","date_passed":"1952-01-07T00:00:00+00:00","date_filed":"1952-01-11T00:00:00+00:00","date_of_signature":"1952-01-11T00:00:00+00:00","date_introduced":"1951-12-31T00:00:00+00:00","index_terms":["FINANCE","BUILDING DEPARTMENT"],"fiscal_note":null,"summary":"An ordinance relating to the 1952 Budget of the Building Department and transferring thereto certain unexpended supplies and expense funds in the 1951 Budget of said department.  ","committee":"Finance"}