{"bill_number":72759,"ordinance_number":81478,"status":"passed","date_passed":"1952-11-17T00:00:00+00:00","date_filed":"1952-11-20T00:00:00+00:00","date_of_signature":"1952-11-20T00:00:00+00:00","date_introduced":"1952-09-22T00:00:00+00:00","index_terms":["FEES","LICENSES","MECHANICAL CODES","ENGINEERS"],"references":"Related: CF 218313; Amends: Ord 80153  ","fiscal_note":null,"summary":"An ordinance relating to refrigeration systems and amending Section 13 of Ordinance No. 80153 to increase certain examination fees.  ","committee":"License"}