{"bill_number":80872,"ordinance_number":89409,"status":"passed","date_passed":"1960-07-05T00:00:00+00:00","date_filed":"1960-07-08T00:00:00+00:00","date_of_signature":"1960-07-08T00:00:00+00:00","date_introduced":"1960-06-27T00:00:00+00:00","index_terms":["LAND ACQUISITION","OLYMPIC HILLS","LAKE CITY","STREETS"],"fiscal_note":null,"summary":"An ordinance accepting deeds from James W. McNett, Sr. and others, to a portion of Lot 5, Block 3, Kennedy's Acre Tracts 2nd Division, and other properties, for street purposes and laying off 28th Ave. Northeast.  ","committee":"Streets and Sewers"}