{"bill_number":104056,"ordinance_number":111580,"status":"passed","date_passed":"1984-03-12T00:00:00+00:00","date_of_signature":"1984-03-16T00:00:00+00:00","date_introduced":"1983-12-12T00:00:00+00:00","index_terms":["SEATTLE CENTER","CONTRACTS","COLISEUM","BASKETBALL"],"fiscal_note":null,"summary":"AN ORDINANCE relating to the Seattle Center Department; authorizing the granting of consent to the substitution of Ackerley Communications, Inc. for the Seattle SuperSonics Corporation in the Agreement authorized by Ordinance 111205.  ","committee":"Parks Community Resources","sponsor":"EXECUTIVE REQUEST","vote":"9-0"}