{"bill_number":86340,"ordinance_number":94815,"status":"passed","date_passed":"1966-05-16T00:00:00+00:00","date_filed":"1966-05-19T00:00:00+00:00","date_of_signature":"1966-05-19T00:00:00+00:00","date_introduced":"1966-05-09T00:00:00+00:00","index_terms":["LOCAL IMPROVEMENT DISTRICTS","STREETS","WATER MAINS","ASSESSMENT","SOUTH BEACON HILL"],"fiscal_note":null,"summary":"AN ORDINANCE authorizing and directing the City Treasurer to cancel certain assessments levied for the improvement of South Thistle Street, et al, by Sewers, Local Improvement District No. 6151, and for the improvement of South Othello Street, et al, by Watermains, etc., Local Improvement District No. 6294, on certain property which has been deeded for street purposes.  ","committee":"Streets and Sewers"}