{"bill_number":89406,"ordinance_number":97857,"status":"passed","date_passed":"1969-06-16T00:00:00+00:00","date_filed":"1969-06-18T00:00:00+00:00","date_of_signature":"1969-06-18T00:00:00+00:00","date_introduced":"1969-06-09T00:00:00+00:00","index_terms":["LICENSES","EMPLOYMENT AGENCIES"],"references":"Related: CF 261291. Amending: Ord 48022.  ","fiscal_note":null,"summary":"AN ORDINANCE repealing Sections 118, 119, 120, 121, 122, 123, 124, 125, 126, 127, 128 and 129 of Ordinance 48022 which provide for the licensing and regulation of employment agencies.  ","committee":"License"}