{"bill_number":89866,"ordinance_number":98303,"status":"passed","date_passed":"1969-10-27T00:00:00+00:00","date_filed":"1969-10-31T00:00:00+00:00","date_of_signature":"1969-10-31T00:00:00+00:00","date_introduced":"1969-10-20T00:00:00+00:00","index_terms":["RIVERVIEW","WEST SEATTLE","EASEMENTS","STORM SEWERS"],"references":"Related: CF 264790  ","fiscal_note":null,"summary":"AN ORDINANCE relating to the Engineering Department, providing for the construction of that portion of the West Marginal Way South comprehensive storm drain trunk system which includes 16th Avenue SW from SW Morgan Street to SW Graham Street, SW Graham Street from 16th Avenue SW to 17th Avenue SW, 17th Avenue SW from SW Graham Street to SW Brandon Street, SW Brandon Street from 17th Avenue SW to 18th Avenue SW, 18th Avenue SW from SW Brandon Street to SW Hudson Street, SW Juneau Street and an easement extending from 16th Avenue SW to 17th Avenue SW, and SW Hudson Street from 18th Avenue SW to a point in Puget Park; and making a reimbursable appropriation from the City Street Fund therefor.  ","committee":"Streets and Sewers"}