{"bill_number":57478,"ordinance_number":66480,"date_passed":"1936-07-20T00:00:00+00:00","date_filed":"1936-07-23T00:00:00+00:00","date_of_signature":"1936-07-23T00:00:00+00:00","date_introduced":"1936-07-13T00:00:00+00:00","index_terms":["US GOVERNMENT","CONTRACTS","WATER SUPPLY","SURVEYS","SKAGIT RIVER","CEDAR RIVER","WATER SUPPLY"],"references":"Related: CF 151644  ","fiscal_note":null,"summary":"An ordinance relating to and providing for the execution of an agreement between the United States Geological Survey and the City of Seattle for the cooperative investigation of the surface water resources of the Skagit and Cedar River Basins; and making an appropriation therefor.  ","committee":"Finance and City Utilities"}