{"bill_number":92517,"ordinance_number":100892,"status":"passed","date_passed":"1972-04-10T00:00:00+00:00","date_filed":"1972-04-14T00:00:00+00:00","date_of_signature":"1972-04-14T00:00:00+00:00","date_introduced":"1972-04-03T00:00:00+00:00","index_terms":["ANTITRUST LITIGATION","WASHINGTON STATE","MANUFACTURING"],"references":"Related: CF 272278  ","fiscal_note":null,"summary":"AN ORDINANCE authorizing the Corporation Counsel to participate on behalf of the City in a class action for damages under federal antitrust laws against certain manufacturers of cast iron pipe.  ","committee":"Utilities"}