{"bill_number":88174,"ordinance_number":96639,"status":"passed","date_passed":"1968-04-22T00:00:00+00:00","date_filed":"1968-04-25T00:00:00+00:00","date_of_signature":"1968-04-25T00:00:00+00:00","date_introduced":"1968-04-15T00:00:00+00:00","index_terms":["LOCAL IMPROVEMENT DISTRICTS","STREETS","PAVING","ASSESSMENT","ALLEYS","FUNDS","ROOSEVELT"],"references":"Related: Ord 95899  ","fiscal_note":null,"summary":"AN ORDINANCE approving and confirming the assessment and assessment roll of Local Improvement District No. 6345 for the improvement of The Alley in Block 5, Green lake Reservoir Addition, being the alley between 19th Avenue Northeast and 20th Avenue Northeast from Northeast 82nd Street to approximately 440 feet north thereof and certain other alleys and a street; paving and otherwise improving the same.  ","committee":"Streets and Sewers"}