{"bill_number":81784,"ordinance_number":90313,"status":"passed","date_passed":"1961-06-12T00:00:00+00:00","date_filed":"1961-06-12T00:00:00+00:00","date_of_signature":"1961-06-12T00:00:00+00:00","date_introduced":"1961-06-05T00:00:00+00:00","index_terms":["ZONING","FIRE PROTECTION","BUILDING CODES","DOWNTOWN"],"references":"Related: CF 242467; Amends: Ord 85500  ","fiscal_note":null,"summary":"An ordinance relating to the Building Code (Ordinance 85500) and amending Section 1601-A thereof to exclude from Fire Zone One a portion of Block 51, D.S. Maynard's Plat of Seattle.  ","committee":"Public Safety"}