{"bill_number":56860,"ordinance_number":65923,"status":"passed","date_passed":"1935-12-16T00:00:00+00:00","date_filed":"1935-12-19T00:00:00+00:00","date_of_signature":"1935-12-19T00:00:00+00:00","date_introduced":"1935-12-09T00:00:00+00:00","index_terms":["FIRE APPARATUS","FIRE DEPARTMENT"],"references":"Related: CF 148823  ","fiscal_note":null,"summary":"An ordinance relating to and directing the Board of Public Works to prepare plans and specifications, to call for bids, and to purchase fire hose, three (3) pumping engines and certain replacement materials for the use of the Fire Department; and providing the funds therefor by budget item transfers.  ","committee":"Public Safety and Finance"}