{"bill_number":56950,"ordinance_number":65995,"status":"passed","date_passed":"1936-01-13T00:00:00+00:00","date_filed":"1936-01-14T00:00:00+00:00","date_of_signature":"1936-01-14T00:00:00+00:00","date_introduced":"1936-01-06T00:00:00+00:00","index_terms":["ETHICS","RETIREMENT SYSTEM","FUNDS","LOCAL IMPROVEMENT DISTRICTS","TRANSFERRING FUNDS"],"fiscal_note":null,"summary":"An ordinance providing the set off of a credit in the \"Employees' Retirement Fund\" in favor of Solon M. Pell against a claim of the Local Improvement Revolving Fund and making the necessary Fund transfer to effectuate the same.  ","committee":"Finance"}