{"bill_number":38023,"ordinance_number":48140,"status":"passed","date_passed":"1924-12-15T00:00:00+00:00","date_filed":"1924-12-24T00:00:00+00:00","date_of_signature":"1924-12-24T00:00:00+00:00","date_introduced":"1924-12-08T00:00:00+00:00","index_terms":["LOCAL IMPROVEMENT DISTRICTS","STREET CONSTRUCTION","PAVING","DRAINAGE","GRADING","ALLEYS","PORTAGE BAY NEIGHBORHOOD","CAPITOL HILL"],"references":"Related: Ord 45796  ","fiscal_note":null,"summary":"An ordinance approving and confirming the assessment and assessment roll of Local Improvement District No. 3728 for the improvement of alley in Block 12, John's Addition and Block 12 Denny-Fuhrman Addition, being the alley between 11th Avenue North and 12th Avenue North, from Edgar Street to Hamlin Street; by paving and otherwise improving the same; under Ordinance No. 45796, and levying and assessing the amounts thereof against the several lots, tracts, parcels of land and other property as shown on said roll, establishing a Local Improvement Fund.  "}