{"bill_number":12503,"ordinance_number":24627,"status":"passed","date_passed":"1910-07-11T00:00:00+00:00","date_filed":"1910-07-14T00:00:00+00:00","date_of_signature":"1910-07-14T00:00:00+00:00","date_introduced":"1910-07-05T00:00:00+00:00","index_terms":["ASSESSMENT","CENTRAL BUSINESS DISTRICT","DOWNTOWN"],"references":"Related: Ord 17700  ","fiscal_note":null,"summary":"An ordinance providing for the rebating and refunding of the excess portions of all assessments levied for the improvement of the alley in C. D. Boren's Addition and the alley in block 11, Boren & Denny's Addition, by paving and constructing a sewers, Ordinance No. 17700 creating Local Improvement District No. 1677.  "}