{"bill_number":9210,"ordinance_number":23373,"status":"passed","date_passed":"1910-02-14T00:00:00+00:00","date_filed":"1910-02-24T00:00:00+00:00","date_of_signature":"1910-02-24T00:00:00+00:00","date_introduced":"1909-08-09T00:00:00+00:00","index_terms":["NOISE","PUBLIC REGULATIONS","BOATS"],"fiscal_note":null,"summary":"An Ordinance prohibiting steamers blowing down boilers while lying at the docks within the limits of the City of Seattle and providing penalties for the violation thereof.  ","committee":"Police and Harbor & Wharves"}