{"bill_number":90421,"ordinance_number":98844,"status":"passed","date_passed":"1970-04-27T00:00:00+00:00","date_filed":"1970-05-01T00:00:00+00:00","date_of_signature":"1970-05-01T00:00:00+00:00","date_introduced":"1970-04-20T00:00:00+00:00","index_terms":["LID","MAPLE LEAF","NORTHGATE","ASSESSMENT","FUNDS","STREETS","PAVING"],"references":"Related: Ord 98023  ","fiscal_note":null,"summary":"AN ORDINANCE approving and confirming the assessment and assessment roll of Local Improvement District No. 6399 for the improvement of 9th Avenue Northeast from Northeast 105th Street to Northeast 106th Street; and a certain other street; by paving the same with three inches of asphaltic concrete on the existing street surface.  ","committee":"Streets and Sewers"}