{"bill_number":35360,"ordinance_number":45617,"status":"passed passed","date_passed":"1923-08-27T00:00:00+00:00","date_filed":"1923-08-29T00:00:00+00:00","date_of_signature":"1923-08-29T00:00:00+00:00","date_introduced":"1923-08-20T00:00:00+00:00","index_terms":["LOCAL IMPROVEMENT DISTRICTS","ALLEYS","PAVING","UNIVERSITY DISTRICT"],"references":"Related: Ord 44634  ","fiscal_note":null,"summary":"An ordinance approving and confirming the assessment and assessment roll of Local Improvement District No. 3610, for the improvement of the alley in block 9. University Park Addition, being the alley between 18th Avenue Northeast and 19th Avenue Northeast, from East 50th Street to East 52nd Street; under Ordinance No. 44634, and levying and assessing the amounts thereof against the several lots, tracts, parcels of land and other property as shown on said roll, establishing a Local Improvement Fund.  ","note":"Council Bill No. 35360 1/2"}