{"bill_number":93896,"ordinance_number":102205,"status":"passed","date_passed":"1973-05-21T00:00:00+00:00","date_filed":"1973-05-31T00:00:00+00:00","date_of_signature":"1973-05-31T00:00:00+00:00","date_introduced":"1973-05-14T00:00:00+00:00","index_terms":["LICENSES","ADVERTISING","CONSUMER PROTECTION","RETAIL TRADE","CLOSING OUT SALES"],"references":"Related: CF 275232. Amending: Ord 48022, Ord 100545.  ","fiscal_note":null,"summary":"AN ORDINANCE relating to and regulating \"Closing Out Sales\" and \"Special Sales,\" and amending Sections 267, 268, 269, and 270 of the License Code (Ordinance 48022) and adding new sections designated Sections 267-1, 267-2, and 270-1 thereto.  ","committee":"Public Safety and Health"}