{"bill_number":37283,"ordinance_number":47444,"status":"passed","date_passed":"1924-07-28T00:00:00+00:00","date_filed":"1924-08-02T00:00:00+00:00","date_of_signature":"1924-08-02T00:00:00+00:00","date_introduced":"1924-07-21T00:00:00+00:00","index_terms":["CITY LIGHT","BUILDING MATERIALS"],"fiscal_note":null,"summary":"An ordinance authorizing expenditures to be incurred by the Lighting Department during the month of August, 1924, for electrical merchandise and construction material.  ","committee":"Finance and City Utilities"}