{"bill_number":85336,"ordinance_number":93825,"status":"passed","date_passed":"1965-04-26T00:00:00+00:00","date_filed":"1965-04-28T00:00:00+00:00","date_of_signature":"1965-04-28T00:00:00+00:00","date_introduced":"1965-04-19T00:00:00+00:00","index_terms":["LOCAL IMPROVEMENT DISTRICTS","FINANCE","ASSESSMENT","WATER MAINS"],"fiscal_note":null,"summary":"AN ORDINANCE appropriating money out of the City property assessment redemption fund, for the purpose of paying assessments on City Property.  ","committee":"Finance"}