{"bill_number":64219,"ordinance_number":72994,"status":"passed","date_passed":"1943-12-13T00:00:00+00:00","date_filed":"1943-12-14T00:00:00+00:00","date_of_signature":"1943-12-14T00:00:00+00:00","date_introduced":"1943-12-06T00:00:00+00:00","index_terms":["WATERWAYS","ASSESSMENT","INTERLOCAL AGREEMENTS","KING COUNTY"],"references":"Related: CF 177870  ","fiscal_note":null,"summary":"An ordinance relating to and authorizing the payment to King County of certain commercial waterway assessments on City property and making an appropriation from the Water Fund therefor.  ","committee":"Finance and City Utilities"}