{"bill_number":98934,"ordinance_number":106911,"status":"passed","date_passed":"1977-11-07T00:00:00+00:00","date_filed":"1977-11-14T00:00:00+00:00","date_of_signature":"1977-11-14T00:00:00+00:00","date_introduced":"1977-10-31T00:00:00+00:00","index_terms":["BONDS","FINANCE","FUNDS","PUBLIC UTILITIES"],"references":"Related: Ord 99997, Res 24976  ","fiscal_note":null,"summary":"AN ORDINANCE relating to the Municipal Sewerage Utility; providing for the issuance of $6, 750,000 par value of \"Seattle Municipal Sewerage Revenue Construction and Refunding Bonds, 1977,\" for the purpose of obtaining the funds with which to refund, pay and retire the outstanding Seattle Municipal Sewerage Bonds, 1971, Series No. 2, and to pay part of the cost of acquiring and constructing certain additions and betterments to and extensions of the Municipal Sewerage System heretofore authorized by Ordinance 99997; fixing the date, form, denomination, maturities, terms and covenants of such bonds; creating a Special fund to provide for the refunding operation; providing for and authorizing the purchase of certain obligations out of proceeds of the sale of such bonds and for the use and application of the money to be derived from such investment; providing for the payment and redemption of the outstanding bonds to be refunded; authorizing the execution of an agreement with a Refunding Trustee; and providing for the public sale of such bonds.  ","committee":"Finance","sponsor":"EXECUTIVE REQUEST","vote":"9-0"}