{"bill_number":103606,"ordinance_number":111104,"status":"passed","date_passed":"1983-04-25T00:00:00+00:00","date_of_signature":"1983-05-03T00:00:00+00:00","date_introduced":"1983-04-11T00:00:00+00:00","index_terms":["CITY LIGHT","ELECTRICITY","UTILITY RATES","PUBLIC REGULATIONS"],"references":"Amending: Ord 110733  ","fiscal_note":null,"summary":"AN ORDINANCE relating to the Seattle City Light Department; providing for the establishment of an average payment plan whereby a customer's expected billings for electricity may be averaged throughout the year in equal installments; and amending Seattle Municipal Code Section 21.49.090 (Section 21.49.090 of Ordinance 110733).  ","committee":"Energy","sponsor":"SMITH","vote":"9-0"}