{"bill_number":94005,"ordinance_number":102299,"status":"passed","date_passed":"1973-06-25T00:00:00+00:00","date_filed":"1973-07-02T00:00:00+00:00","date_of_signature":"1973-07-02T00:00:00+00:00","date_introduced":"1973-06-18T00:00:00+00:00","index_terms":["LAND ACQUISITION","DEPARTMENT OF COMMUNITY DEVELOPMENT","URBAN RENEWAL PROGRAM","LESCHI","CENTRAL AREA"],"references":"Related: CF 275769, Ord 98876  ","fiscal_note":null,"summary":"AN ORDINANCE relating to the South Leschi Action Area Urban Renewal project (NDP No. Wash. A-2); authorizing acquisition of property in Wood's Supplemental Plat of blocks 16 and 17, Burke's Second Addition to Seattle; block 1, Lewis and Gilman's Addition to the City of Seattle; and in block 6, Baxter's Addition to the City of Seattle.  ","committee":"Parks and Public Grounds"}