{"bill_number":94701,"ordinance_number":102976,"status":"passed","date_passed":"1974-01-21T00:00:00+00:00","date_filed":"1974-01-29T00:00:00+00:00","date_of_signature":"1974-01-29T00:00:00+00:00","date_introduced":"1974-01-14T00:00:00+00:00","index_terms":["LAND ACQUISITION","PARKS","GREENBELTS","TRAILS","MADRONA","HARRISON","DENNY BLAINE","CENTRAL AREA"],"references":"Related: CF 277696, Ord 100526  ","fiscal_note":null,"summary":"AN ORDINANCE relating to the Department of Parks and Recreation, providing for the purchase of Lots 1 through 8, inclusive, and Lot 17, Block 2 of Meddell's Madrona Park Addition, and authorizing payment therefor from the appropriation heretofore made by Ordinance 100526 for the Harrison Ridge Greenbelt-Trail project.  ","committee":"Parks and Public Grounds","sponsor":"CHAPMAN"}