{"bill_number":2322,"ordinance_number":12932,"status":"passed","date_passed":"1905-10-16T00:00:00+00:00","date_filed":"1905-10-23T00:00:00+00:00","date_of_signature":"1905-10-23T00:00:00+00:00","date_introduced":"1905-09-05T00:00:00+00:00","index_terms":["STREET CONSTRUCTION","WATER MAINS","FIRE HYDRANTS","STEVENS","CAPITOL HILL"],"references":"Related: 28269  ","fiscal_note":null,"summary":"An Ordinance providing for the improvement of East Prospect Street, from Nineteenth Avenue North to Twenty-third Avenue North; Twentieth Avenue North, from East Roy Street to East Galer Street; Twenty-first Avenue North, from the south line of Capitol Hill Addition, Division No. 6, to East Galer Street; Twenty-second Avenue North, from East Mercer Street to East Galer Street; Twenty-third Avenue North, from East Mercer Street to East Prospect Street; East Roy Street, from Nineteenth Avenue North to Twenty-third Avenue North; and East Mercer Street, from Twenty-first Avenue North to Twenty-third Avenue North, all in the City of Seattle, by constructing water mains of proper dimensions, together with all necessary gates, tees, crosses, fire hydrants and other appurtenances necessary for the reasonable water service and fire protection of said portions of said streets and avenues, in accordance with Majority Petition, being File No. 28269 in the office of the City Comptroller of the City of Seattle, and providing for the payment therefor by the mode of \"Payment by Bonds,\" as provided by an act of the Legislature of the State of Washington, entitled \"An act authorizing the issuance and sale of bonds by cities, to pay for local improvements, providing for the payment thereof, and declaring an emergency,\" approved March 14, 1899, and Ordinance No. 5693 of said city, approved December 6, 1899.  "}