{"bill_number":2380,"ordinance_number":15649,"status":"passed","date_passed":"1907-03-25T00:00:00+00:00","date_filed":"1907-03-28T00:00:00+00:00","date_of_signature":"1907-03-28T00:00:00+00:00","date_introduced":"1907-03-18T00:00:00+00:00","index_terms":["ASSESSMENT","PUBLIC REGULATIONS"],"references":"Repealing: Ord 478  ","fiscal_note":null,"summary":"An Ordinance repealing Ordinance No. 478, being an ordinance in relation to the payment of assessments for street improvements, approved October 20, 1883.  "}