{"bill_number":2534,"ordinance_number":15795,"status":"passed","date_passed":"1907-04-15T00:00:00+00:00","date_filed":"1907-04-18T00:00:00+00:00","date_of_signature":"1907-04-18T00:00:00+00:00","date_introduced":"1907-04-08T00:00:00+00:00","index_terms":["STREET CONSTRUCTION","GRADING","PAVING","UNIVERSITY DISTRICT","RAVENNA"],"references":"Related: Res 522  ","fiscal_note":null,"summary":"An Ordinance providing for the improvement of Twenty-fifth Avenue Northeast from East Fifty-fourth Street to Northern Pacific Railway Company right of way, all in the City of Seattle, by grading and curbing, in accordance with Resolution No. 522 of the City Council of the City of Seattle, and providing for the payment therefor by the mode of \"Payment by Bonds,\" as provided by the laws of the State of Washington and the Charter and Ordinances of the City of Seattle  "}