{"bill_number":62092,"ordinance_number":70906,"status":"passed","date_passed":"1941-05-29T00:00:00+00:00","date_of_signature":null,"date_introduced":"1941-05-28T00:00:00+00:00","index_terms":["WOOD PRODUCTS INDUSTRY","TIMBER","CEDAR RIVER","WATERSHEDS","CONTRACTS"],"references":"Related: Ord 37496, Ord 37645, Ord 70482  ","fiscal_note":null,"summary":"An ordinance relating to and authorizing the Superintendent of Water of compromise and settle with the Trustee in Bankruptcy of Pacific States Lumber Company all remaining matters arising out of said company's logging operations in the Cedar River Watershed.  ","committee":"City Utilities"}