{"bill_number":60307,"ordinance_number":69181,"status":"passed","date_passed":"1939-05-08T00:00:00+00:00","date_filed":"1939-05-09T00:00:00+00:00","date_of_signature":"1939-05-09T00:00:00+00:00","date_introduced":"1939-05-01T00:00:00+00:00","index_terms":["BUILDING DEPARTMENT","WAGES AND SALARIES","CITY EMPLOYEES"],"fiscal_note":null,"summary":"An ordinance relating to the Building Department; creating therein a position of \"Assistant Auditorium Manager\": defining the duties and fixing the compensation thereof; providing the manner of payment of such compensation; and abolishing one position of \"Clerk-Stenographer\" therein.  ","committee":"Finance and Department Efficiency"}