{"bill_number":115625,"status":"retired 3/30/09","date_introduced":"2006-07-10T00:00:00+00:00","index_terms":["STREET USE PERMITS","STREETS","SHORELANDS","INDUSTRIAL DISTRICTS","FEES","PUBLIC REGULATIONS"],"references":"Related: ORd 119673  ","fiscal_note":"[Fiscal Note to Council Bill](http://clerk.seattle.gov/~public/fnote/115625.htm)[](#h1)[](#h3)115625","summary":"AN ORDINANCE granting Lakeside Industries, a maritime industrial business, permission to occupy the NW 39th Street shoreline street end right-of-way for a ten (10) year term; specifying the conditions under which this permit is granted; and providing for acceptance of the permit and conditions.  ","committee":"Transportation","sponsor":"DRAGO"}